{
    "uuids": {
        "phone_id": "5703df48-ad20-4b8c-a4bc-2606f2e44970",
        "uuid": "9ebc81d7-5cbe-4677-b373-45a6b9771d5f",
        "client_session_id": "cb1152ad-4d61-4afd-884e-e5abf8221bfe",
        "advertising_id": "5e1a6351-9070-4d40-8394-618269f81982",
        "android_device_id": "android-eb52e99ecea84f31",
        "request_id": "91ca1478-f22a-4f1b-ba44-82ecbd17f67c",
        "tray_session_id": "d411eb70-618c-4833-aa05-f24fc6bb3bbd"
    },
    "mid": "aIOO1AABAAGFd_z0V9TE0QylQ439",
    "ig_u_rur": null,
    "ig_www_claim": null,
    "authorization_data": {
        "ds_user_id": "75997586422",
        "sessionid": "75997586422%3ASowvMmXvdxZ3jC%3A1%3AAYdedGUnZn3e66PNsSSBkz99JyV9lt9neOq95ANlmA"
    },
    "cookies": {},
    "last_login": 1753452253.8995264,
    "device_settings": {
        "app_version": "269.0.0.18.75",
        "android_version": 26,
        "android_release": "8.0.0",
        "dpi": "480dpi",
        "resolution": "1080x1920",
        "manufacturer": "OnePlus",
        "device": "devitron",
        "model": "6T Dev",
        "cpu": "qcom",
        "version_code": "314665256"
    },
    "user_agent": "Instagram 269.0.0.18.75 Android (26/8.0.0; 480dpi; 1080x1920; OnePlus; 6T Dev; devitron; qcom; en_US; 314665256)",
    "country": "US",
    "country_code": 1,
    "locale": "en_US",
    "timezone_offset": -14400
}